{"version":1,"resource":"file:///home/fufu/.config/waybar/config.jsonc","entries":[{"id":"6DAh.jsonc","timestamp":1682785588594},{"id":"iaXb.jsonc","source":"undoRedo.source","timestamp":1682785592958},{"id":"69oW.jsonc","timestamp":1682785602157},{"id":"2OjU.jsonc","source":"undoRedo.source","timestamp":1682785605201},{"id":"dUFb.jsonc","timestamp":1682785652884},{"id":"OcEm.jsonc","timestamp":1682785732107},{"id":"NfJM.jsonc","timestamp":1682785805447},{"id":"NrDa.jsonc","timestamp":1682785853816},{"id":"7VzX.jsonc","timestamp":1682785883736},{"id":"3P9z.jsonc","timestamp":1682785978153},{"id":"OkT0.jsonc","timestamp":1682786007609},{"id":"XZK6.jsonc","timestamp":1682786799320},{"id":"tz0h.jsonc","source":"undoRedo.source","timestamp":1682786803030},{"id":"ZNS0.jsonc","timestamp":1682787007049}]}